nonebot/adapters/gewechat/__init__.py
nonebot/adapters/gewechat/adapter.py
nonebot/adapters/gewechat/api_model.py
nonebot/adapters/gewechat/bot.py
nonebot/adapters/gewechat/config.py
nonebot/adapters/gewechat/event.py
nonebot/adapters/gewechat/event_store.py
nonebot/adapters/gewechat/exception.py
nonebot/adapters/gewechat/message.py
nonebot/adapters/gewechat/model.py
nonebot/adapters/gewechat/template.py
nonebot/adapters/gewechat/utils.py
nonebot_adapter_gewechat-0.5.2.dist-info/LICENSE.txt
nonebot_adapter_gewechat-0.5.2.dist-info/METADATA
nonebot_adapter_gewechat-0.5.2.dist-info/WHEEL
nonebot_adapter_gewechat-0.5.2.dist-info/RECORD
