Metadata-Version: 2.3
Name: nonebot-adapter-gewechat
Version: 0.5.2
Summary: NoneBot adapter for WeChat
License: MIT
Author: RF-Tar-Railt
Author-email: rf_tar_railt@qq.com
Requires-Python: <4.0,>=3.9
Classifier: License :: OSI Approved :: MIT License
Classifier: Programming Language :: Python :: 3
Classifier: Programming Language :: Python :: 3.9
Classifier: Programming Language :: Python :: 3.10
Classifier: Programming Language :: Python :: 3.11
Classifier: Programming Language :: Python :: 3.12
Classifier: Programming Language :: Python :: 3.13
Provides-Extra: png
Requires-Dist: nonebot2 (>=2.4.2)
Requires-Dist: pydantic (>=1.10.0,!=2.5.0,!=2.5.1,<3.0.0)
Requires-Dist: pypng (>=0.20220715.0) ; extra == "png"
Requires-Dist: qrcode (>=8.0,<9.0)
Requires-Dist: selectolax (>=0.3.28,<1.0.0)
Requires-Dist: ujson (>=5.10.0,<6.0.0)
Project-URL: Homepage, https://github.com/Shine-Light/nonebot-adapter-gewechat
Project-URL: Repository, https://github.com/Shine-Light/nonebot-adapter-gewechat
